MANIFEST.in
README.rst
setup.py
lccm/__init__.py
lccm/lccm.py
lccm.egg-info/PKG-INFO
lccm.egg-info/SOURCES.txt
lccm.egg-info/dependency_links.txt
lccm.egg-info/requires.txt
lccm.egg-info/top_level.txt