Metadata-Version: 1.1
Name: lccm
Version: 0.1.20
Summary: Estimation of latent class choice models using Expectation Maximization algorithm
Home-page: https://github.com/ferasz/LCCM
Author: Feras El Zarwi and Akshay Vij
Author-email: feraselzarwi@gmail.com, vij.akshay@gmail.com
License: BSD License
Keywords: latent class choice models Expectation Maximization algorithm discrete choice modeling econometrics
Platform: UNKNOWN
Classifier: Development Status :: 2 - Pre-Alpha
Classifier: Intended Audience :: Science/Research
Classifier: Intended Audience :: End Users/Desktop
Classifier: Intended Audience :: Developers
Classifier: Topic :: Scientific/Engineering
Classifier: License :: OSI Approved :: BSD License
Classifier: Programming Language :: Python :: 2
Classifier: Programming Language :: Python :: 2.7
